Metadata-Version: 1.1
Name: problem
Version: 0.2.3
Summary: Need more problem ??
Home-page: https://github.com/yingkhun/problem/
Author: Yingkhun
Author-email: yingkhunn@gmail.com
License: MIT
Download-URL: https://github.com/yingkhun/problem/archive/v0.2.3.zip
Keywords: problem,problemm,problemmm
Platform: UNKNOWN
Classifier: Development Status :: 3 - Alpha
Classifier: Intended Audience :: Developers
Classifier: Topic :: Software Development :: Build Tools
Classifier: License :: OSI Approved :: MIT License
Classifier: Programming Language :: Python :: 3
Classifier: Programming Language :: Python :: 3.4
Classifier: Programming Language :: Python :: 3.5
Classifier: Programming Language :: Python :: 3.6
Classifier: Programming Language :: Python :: 3.7
Classifier: Programming Language :: Python :: 3.8
Classifier: Programming Language :: Python :: 3.9
